sustech_rawr/__init__.py
sustech_rawr/main.py
sustech_rawr-1.0.5.dist-info/licenses/LICENSE
sustech_rawr-1.0.5.dist-info/METADATA
sustech_rawr-1.0.5.dist-info/WHEEL
sustech_rawr-1.0.5.dist-info/entry_points.txt
sustech_rawr-1.0.5.dist-info/top_level.txt
sustech_rawr-1.0.5.dist-info/RECORD
